{
  "page": {
    "width": 2008,
    "height": 1241
  },
  "objects": [
    {
      "id": 1,
      "text": "強化生物多樣性保護\n台積公司關注環境永續，積極營造科技與生態平衡，為確保生態系統永續使用並維持生物多樣性，透過定期檢視營運廠區的生態變化，長期培育在地原生種，於廠內建置螢火蟲棲地、推動台積電植樹薪傳計畫，使物種穩定成長繁衍。除持續實踐友善生態作為，台積公司亦積極呼應聯合國生物多樣性公約及永續發展目標，於民國111年擬定《生物多樣性宣言》、民國112年正式發布，承諾與利害關係人共同保護與深化生物多樣性完整度，並攜手供應鏈夥伴一同提升認知，在其營運活動範圍內應遵守生物多樣性保育相關法規，落實強化環保使命。\n\n為更深入了解營運與在地環境的關聯性，台積公司民國111年第4季啟動「自然與生物多樣性依賴及衝擊評估」，依營運廠址所在地、汙染物排放、生態系統服務依賴度三面向進行分析。營運廠址所在地方面，運用林務局「國土生態保育綠色網絡地理資訊」資料庫為基準，比對台灣各廠址、並納入營運過程中的資源使用及物質排放做為評估因子，以辨識具體的減緩或復育方向；比對結果顯示，台灣各營運據點周邊2公里內皆非野生動物保護區或自然保留區範圍，台積公司除持續維護廠區綠色生態、落實環境教育外，亦同步與林務局、縣市政府、學研單位與保育組織等利害關係團體合作，針對廠區周邊範圍評估推展相關保育計畫的機會點，藉以深化生物多樣性的多元價值。\n\n汙染物排放調查方面，透過生命週期衝擊（Life Cycle Impact）的量化分析發現，溫室氣體排放是造成生物多樣性衝擊的主因，其次為水資源使用，台積公司藉由推動低碳製造並持續強化溫室氣體減量標竿作為，有效降低單位產品的溫室氣體排放，並依循AWS標準落實各廠區水資源永續管理，同時優化廠區周邊生態與水土保持，有助生物多樣性發展。而生態系統服務依賴度則為首次調查，除內部專責單位外，台積公司亦邀請外部專家加入會議進行討論，同時針對供應商執行問卷調查；綜合評估結果顯示，台積公司與供應鏈對水資源供給、氣候調節、河川防洪3種服務項目的依賴程度較高，台積公司將依氣候風險調適作為準則持續提升組織氣候韌性、推動綠色低碳供應鏈並強化管理，以降低對生態系統服務的依賴度，並減緩生態系統服務失能時對營運造成的影響。",
      "bbox": [
        95,
        246,
        1917,
        1106
      ],
      "type": "paragraph",
      "bbox_pdf": [
        45.59716274063901,
        117.99991639019692,
        920.1027470926839,
        530.5199492990155
      ],
      "retrieval": [
        {
          "code": "TC-SC-150a.1",
          "text": "廢棄物管理。製造過程中產生之有害廢棄物重量，再循環百分比。",
          "score": 0.7189403772354126
        },
        {
          "code": "TC-SC-110a.2",
          "text": "溫室氣體排放。對管理範疇 1 排放之長期及短期策略或計畫、排放減量目標，以及針對該等目標之績效分析之討論。",
          "score": 0.6811614036560059
        },
        {
          "code": "TC-SC-140a.1",
          "text": "水管理。總取水量，於基線水壓力高或極高區域之百分比；總耗水量，於基線水壓力高或極高區域之百分比。",
          "score": 0.6677002906799316
        },
        {
          "code": "TC-SC-000.B",
          "text": "一般資訊。自有場所產量之百分比。",
          "score": 0.6273987293243408
        },
        {
          "code": "TC-SC-440a.1",
          "text": "材料取得。與關鍵材料之使用有關風險管理之描述。",
          "score": 0.6052610874176025
        }
      ]
    },
    {
      "id": 2,
      "text": "生物多樣性推動歷程\n\n開始推動綠建築並關注生物多樣性概念\n台中晶圓十五廠第一期廠區培育在地物種\n成立生態志工團隊\n新竹晶圓十二廠第四期廠區打造首座自然護岸的生態水池\n台中晶圓十五廠第五期廠區營造首座近自然林\n啟動國內半導體業首例自主性生態調查\n台南晶圓十四廠成功復育螢火蟲\n首獲環保署「環境教育設施場所」認證\n啟動「台積電植樹薪傳計畫」\n新竹及台中廠區開始復育螢火蟲\n擬定《生物多樣性宣言》\n進行營運廠區「自然與生物多樣性依賴及衝擊評估」\n植樹計畫累積種植12.2萬棵樹木",
      "bbox": [
        95,
        707,
        1917,
        1106
      ],
      "type": "line",
      "bbox_pdf": [
        45.59716274063901,
        339.1298410075985,
        920.1027470926839,
        530.5199492990155
      ],
      "retrieval": [
        {
          "code": "TC-SC-150a.1",
          "text": "廢棄物管理。製造過程中產生之有害廢棄物重量，再循環百分比。",
          "score": 0.6542366147041321
        },
        {
          "code": "TC-SC-110a.2",
          "text": "溫室氣體排放。對管理範疇 1 排放之長期及短期策略或計畫、排放減量目標，以及針對該等目標之績效分析之討論。",
          "score": 0.623834490776062
        },
        {
          "code": "TC-SC-110a.1",
          "text": "溫室氣體排放。範疇 1 之全球總排放量及來自全氟化合物之總排放量。",
          "score": 0.5759359002113342
        },
        {
          "code": "TC-SC-140a.1",
          "text": "水管理。總取水量，於基線水壓力高或極高區域之百分比；總耗水量，於基線水壓力高或極高區域之百分比。",
          "score": 0.5691716074943542
        },
        {
          "code": "TC-SC-000.B",
          "text": "一般資訊。自有場所產量之百分比。",
          "score": 0.5244327783584595
        }
      ]
    }
  ]
}