{
  "page": {
    "width": 1754,
    "height": 1241
  },
  "objects": [
    {
      "id": 0,
      "text": "本公司接獲檢舉案件後，依案件類型由董事會稽核處或指定權責單位進行調查，如處理檢舉案件人員發現檢舉事項對於其有自身利害關係者，應自行迴避，若經調查後發現致使本公司或子公司有重大違規情事或有受重大損害之虞時，應立即作成報告，並書面通知本公司獨立董事；有重大偶發或違法案件之情事，應主動向相關機關通報或告發。\n\n檢舉案件之所有受理及調查過程、調查結果與相關文件，應製作紀錄留存，調查結果應送交誠信經營委員會備查，並應將檢舉情事、其處理方式及後續檢討改善措施向董事會報告，如被檢舉人為本公司及子公司董事、監察人或職責相當於副總經理以上之管理階層者，應先呈報本公司獨立董事，調查報告應陳報至本公司審計委員會複審，其餘分別由董事會稽核處／子公司或董事會稽核處指定與被檢舉人無利益衝突且具職權行使獨立性之權責單位調查；被檢舉人涉及本公司總稽核或董事會稽核處所屬人員時，由法遵處或由法遵處指定具職權行使獨立性之權責單位調查；若查有不誠信或不法行為相關事證者，應向本公司董事會報告。\n\n除無法聯絡檢舉人之情形外，調查完結後 30 日內應將調查結果以書面或其他方式通知檢舉人。如符合應報送主管機關之稽核報告者，應於調查結束日起 2 個月內向主管機關辦理申報。\n\n檢舉人之身分資料應予以保密，不得洩漏足以識別其身分之資訊，並且不得因所檢舉案件而對檢舉人予以解僱、解任、調降、減薪、損害其依法令、契約或習慣上所應享有之權利，或為其他不利處分。\n\n檢舉案件經查證屬實者，本公司或子公司除應對被檢舉人及涉案人員依相關懲戒辦法辦理外，得依檢舉情事之情節輕重酌予檢舉人獎勵；內部人員如有虛報或惡意指控之情事，應予議處，以期強化並深植誠信、透明的企業文化。",
      "bbox": [
        116,
        158,
        852,
        1144
      ],
      "type": "paragraph",
      "bbox_pdf": [
        55.67801693227979,
        75.78856418557363,
        408.9454347095033,
        548.7475786601027
      ]
    },
    {
      "id": 1,
      "text": "2022 年檢舉案件處理情形\n2022 年本集團未有發生損害檢舉人權益或予以不利處分之情事。2022 年本集團檢舉信箱受理案件共 6 件，均已完成調查報告並結案，查無違法事證，惟其中 1 件確有檢舉所陳管理階層之領導等問題，業經金控函請子公司督導改善。本集團 2022 年度受理檢舉案件之調查結果，已依本公司檢舉辦法報送誠信經營委員會備查。",
      "bbox": [
        1002,
        158,
        2346,
        337
      ],
      "type": "paragraph",
      "bbox_pdf": [
        480.9428703977961,
        75.78856418557363,
        841.8900146484375,
        161.65029196543236
      ]
    },
    {
      "id": 2,
      "text": "受理檢舉案件共計 6 件\t屬實 1 件，不屬實 5 件\n外部檢舉\t具名\t0\t屬實\t0\n\t\t不屬實\t0\n不具名 / 匿名\t4\t屬實\t0\n\t\t不屬實\t4\n檢舉案件數\t內部檢舉\t具名\t1\t屬實\t1\n\t\t不屬實\t0\n不具名 / 匿名\t1\t屬實\t0\n\t\t不屬實\t1",
      "bbox": [
        1002,
        396,
        2346,
        722
      ],
      "type": "table",
      "bbox_pdf": [
        480.9428703977961,
        189.9510849208048,
        841.8900146484375,
        346.32495786065925
      ]
    },
    {
      "id": 3,
      "text": "合庫金控誠信經營檢舉管道\n檢舉電子信箱：5134@tcfhc.com.tw\n檢舉專線電話：(02) 2173-8913",
      "bbox": [
        527,
        900,
        852,
        1012
      ],
      "type": "paragraph",
      "bbox_pdf": [
        252.95099071820215,
        431.7070111836473,
        408.9454347095033,
        485.4305503531678
      ]
    }
  ]
}