{
  "page": {
    "width": 2481,
    "height": 1754
  },
  "objects": [
    {
      "id": 1,
      "text": "2.2 公司治理管理方針",
      "bbox": [
        169,
        137,
        436,
        181
      ],
      "type": "line",
      "bbox_pdf": [
        81.09752448688155,
        65.75765792864078,
        209.22201583597843,
        86.87690573054002
      ],
      "retrieval": [
        {
          "code": "IF-GU-000.B",
          "text": "一般資訊。向住宅、商業、工業客戶供應之天然氣量，以及轉供第三方之天然氣量。",
          "score": 0.3792315423488617
        },
        {
          "code": "IF-GU-420a.2",
          "text": "終端使用效率。依市場別呈現因效率措施所節省之天然氣量。",
          "score": 0.36950770020484924
        },
        {
          "code": "IF-GU-000.C",
          "text": "一般資訊。天然氣輸氣管線、配氣管線之長度。",
          "score": 0.34894639253616333
        },
        {
          "code": "IF-GU-000.A",
          "text": "一般資訊。住宅、商業、工業客戶數。",
          "score": 0.34808868169784546
        },
        {
          "code": "IF-GU-540a.4",
          "text": "天然氣輸送基礎設施完整性。說明管理天然氣輸送基礎設施完整性之措施，包括與安全及排放相關之風險。",
          "score": 0.3038194179534912
        }
      ]
    },
    {
      "id": 2,
      "text": "<table><tr><th>目標／項目</th><th>利害關係人</th><th>承諾 (政策)</th><th>2022年執行情形 (行動)</th></tr><tr><td>保障股東權益(G)</td><td>股東</td><td>• 鼓勵股東多使用電子投票參與股東會<br>• 持續配發股利<br>• 每季至少召開1次董事會</td><td>• 為強化公司治理，股權1%以上股東得依《公司法》相關規定行使提案權，並鼓勵股東多使用電子投票參與股東會表決及選舉。為響應環保減碳，手冊及年報紙本印製較去年共減量160本。<br>• 發放每股現金股利1.1元。<br>• 依法設置獨立董事3席，強化並落實董事會運作之獨立性。</td></tr><tr><td>強化董事會職能(G)</td><td>董事</td><td>• 董事會成員多元化政策及績效評估<br>• 強化董事會職能發揮及進修<br>• 加強防範內線交易之宣導</td><td>• 露並落實董事會成員多元化政策。<br>• 執行董事會及功能性委員會之績效評估，評估週期、面向、內容及結果請詳111年報第23~25頁。<br>• 提供董事多元的進修課程資訊並協助報名。<br>• 配合主關機關規定，強化防範內線交易之宣導作業，避免董事觸法。</td></tr><tr><td>提昇資訊透明度(G)</td><td>股東、員工、供應商、社區居民</td><td>• 強化資訊揭露<br>• 與利害關係人保持暢通之溝通管道<br>• 儲氣槽安全資訊</td><td>• 依規定揭露公司各項資訊於官網及公開資訊觀測站(9908)。<br>• 設置發言人、代理發言人及公司治理主管。<br>• 每年召開法人說明會。<br>• 公司網站設置利害關係人專區。<br>• 各項最新消息公告更新於官網。</td></tr></table>",
      "bbox": [
        169,
        233,
        1797,
        1031
      ],
      "type": "table",
      "bbox_pdf": [
        81.09752448688155,
        111.8360167691482,
        862.3210148102139,
        494.86237463086604
      ],
      "retrieval": [
        {
          "code": "IF-GU-000.A",
          "text": "一般資訊。住宅、商業、工業客戶數。",
          "score": 0.6658711433410645
        },
        {
          "code": "IF-GU-420a.2",
          "text": "終端使用效率。依市場別呈現因效率措施所節省之天然氣量。",
          "score": 0.588573157787323
        },
        {
          "code": "IF-GU-000.B",
          "text": "一般資訊。向住宅、商業、工業客戶供應之天然氣量，以及轉供第三方之天然氣量。",
          "score": 0.5708262920379639
        },
        {
          "code": "IF-GU-000.C",
          "text": "一般資訊。天然氣輸氣管線、配氣管線之長度。",
          "score": 0.5471177101135254
        },
        {
          "code": "IF-GU-540a.2",
          "text": "天然氣輸送基礎設施完整性。配送管線中：鑄鐵或鍛鐵、未受保護之鋼管的百分比。",
          "score": 0.4142736792564392
        }
      ]
    },
    {
      "id": 3,
      "text": "2.2.1 對影響產業之環境及社會議題相關法規之因應\n2022年雖經中央主管機關以違反天然氣事業法裁罰罰鍰處分30萬元，但本公司猶認並無違法而向行政院提起訴願，力陳秉持工程專業設計並重視用戶需求，確實依法經營業務，終獲受理訴願機關撤銷罰鍰處分，因而，本公司2022年並無違反天然氣事業法之情事。\n\n本公司為取得公用天然氣設立許可暨供氣營業執照之業者，經營導管燃氣與供應民生用天然氣之銷售行為皆有法令規範，並切實遵循。蒐集法令新訊、國內外有關天然氣技術、施工管理或相關管線工程之新聞，以電子郵件傳遞予各單位通知同仁；定期遵循ISO50001能源管理系統、ISO45001/TOSHMS職業安全衛生管理系統、ISO9001品質管理系統辦理法令規章查詢作業，摘錄修法要旨並文件化，作為法令遵循作業隨時翻閱查考之憑據。",
      "bbox": [
        169,
        1104,
        1797,
        1577
      ],
      "type": "paragraph",
      "bbox_pdf": [
        81.09752448688155,
        529.9011266658352,
        862.3210148102139,
        756.933040536252
      ],
      "retrieval": [
        {
          "code": "IF-GU-540a.1",
          "text": "天然氣輸送基礎設施完整性。可通報之管線事故、接獲之矯正行動、違反管線安全法規之件數。",
          "score": 0.8445214033126831
        },
        {
          "code": "IF-GU-540a.3",
          "text": "天然氣輸送基礎設施完整性。已檢查之天然氣輸氣管線、配氣管線百分比。",
          "score": 0.7802524566650391
        },
        {
          "code": "IF-GU-420a.2",
          "text": "終端使用效率。依市場別呈現因效率措施所節省之天然氣量。",
          "score": 0.75859534740448
        },
        {
          "code": "IF-GU-540a.4",
          "text": "天然氣輸送基礎設施完整性。說明管理天然氣輸送基礎設施完整性之措施，包括與安全及排放相關之風險。",
          "score": 0.7448791265487671
        },
        {
          "code": "IF-GU-240a.4",
          "text": "能源可負擔性。說明外部因素(包含服務區域經濟狀況)對天然氣可負擔性的影響。",
          "score": 0.671123743057251
        }
      ]
    },
    {
      "id": 4,
      "text": "2.3 股東會\n股東常會之召開，依公司法規定須於會計年度終了後6個月內由董事會依法召開，確保股東對公司重大事項享有知悉及參與表決的權利。本公司2022年依候選人提名制規定，由董事會提名候選人名單並公告之，於股東會進行第20屆董事選舉，本屆董事會成員改選後從15人減至11人，股東會各項相關資料依規定申報至公開資訊觀測站，並揭露於公司官網。",
      "bbox": [
        2063,
        233,
        3464,
        374
      ],
      "type": "paragraph",
      "bbox_pdf": [
        989.9656391505126,
        111.8360167691482,
        1190.550048828125,
        179.51360631614347
      ],
      "retrieval": [
        {
          "code": "IF-GU-000.A",
          "text": "一般資訊。住宅、商業、工業客戶數。",
          "score": 0.3734644055366516
        },
        {
          "code": "IF-GU-000.B",
          "text": "一般資訊。向住宅、商業、工業客戶供應之天然氣量，以及轉供第三方之天然氣量。",
          "score": 0.3514116406440735
        },
        {
          "code": "IF-GU-420a.2",
          "text": "終端使用效率。依市場別呈現因效率措施所節省之天然氣量。",
          "score": 0.3361087441444397
        },
        {
          "code": "IF-GU-000.C",
          "text": "一般資訊。天然氣輸氣管線、配氣管線之長度。",
          "score": 0.31479698419570923
        },
        {
          "code": "IF-GU-240a.4",
          "text": "能源可負擔性。說明外部因素(包含服務區域經濟狀況)對天然氣可負擔性的影響。",
          "score": 0.27113673090934753
        }
      ]
    },
    {
      "id": 5,
      "text": "2.4 董事會\n2.4.1 董事會組成\n2022年共召開6次董事會議，董事實際出席率達85.89%(不含委託)，董事會決議揭露於公司官網。依公司章程規定，設置董事11人(含獨立董事3人)，由股東會就有行為能力之人依法選任之。董事任期3年，連選得連任。董事會在本公司的企業管理機制中，職司領導經營與業務運作，以及監督業務策略的執行情況，領導方向以法律規定範圍內符合公益及其股東利益的方式為之，且行事方式均不得違反法令規定，董事對於會議事項，與其自身或其代表之法人有利害關係者，應於當次董事會說明其利害關係之重要內容，如有害於公司利益之虞時，不得加入討論及表決，且討論及表決時應予迴避，並不得代理其他董事行使其表決權。",
      "bbox": [
        2063,
        650,
        3464,
        957
      ],
      "type": "paragraph",
      "bbox_pdf": [
        989.9656391505126,
        311.98888798260225,
        1190.550048828125,
        459.3436396913082
      ],
      "retrieval": [
        {
          "code": "IF-GU-000.A",
          "text": "一般資訊。住宅、商業、工業客戶數。",
          "score": 0.4374341368675232
        },
        {
          "code": "IF-GU-420a.2",
          "text": "終端使用效率。依市場別呈現因效率措施所節省之天然氣量。",
          "score": 0.42316943407058716
        },
        {
          "code": "IF-GU-000.C",
          "text": "一般資訊。天然氣輸氣管線、配氣管線之長度。",
          "score": 0.41580522060394287
        },
        {
          "code": "IF-GU-000.B",
          "text": "一般資訊。向住宅、商業、工業客戶供應之天然氣量，以及轉供第三方之天然氣量。",
          "score": 0.401314377784729
        },
        {
          "code": "IF-GU-540a.2",
          "text": "天然氣輸送基礎設施完整性。配送管線中：鑄鐵或鍛鐵、未受保護之鋼管的百分比。",
          "score": 0.32520100474357605
        }
      ]
    },
    {
      "id": 6,
      "text": "2.4.2 董事會成員多元化政策\n本公司董事會多元化政策，董事會成員之遴選條件不侷限於性別、年齡、國籍及文化等條件，且著重於應具備相關專業資格與經驗為優先條件。為達到理想的公司治理目標，董事會整體應具備營運決策判斷力、危機處理能力、產業發展及科技新知洞察力、永續發展前瞻力、會計及財務分析能力。\n\n第20屆董事會成員皆為本國籍，女性董事減少1人，女性董事比例較上屆13.3%降低為9.1%，而70歲以上董事比例較上屆46.7%增加至54.5%，為增進董事成員多元化政策成效，目標希望增加60歲以下董事及女性董事比例分別達到27%及18%。",
      "bbox": [
        2063,
        1237,
        3464,
        1591
      ],
      "type": "paragraph",
      "bbox_pdf": [
        989.9656391505126,
        593.7388529761215,
        1190.550048828125,
        763.6528012004926
      ],
      "retrieval": [
        {
          "code": "IF-GU-000.A",
          "text": "一般資訊。住宅、商業、工業客戶數。",
          "score": 0.6442562341690063
        },
        {
          "code": "IF-GU-420a.2",
          "text": "終端使用效率。依市場別呈現因效率措施所節省之天然氣量。",
          "score": 0.5616812705993652
        },
        {
          "code": "IF-GU-000.B",
          "text": "一般資訊。向住宅、商業、工業客戶供應之天然氣量，以及轉供第三方之天然氣量。",
          "score": 0.5399889349937439
        },
        {
          "code": "IF-GU-000.C",
          "text": "一般資訊。天然氣輸氣管線、配氣管線之長度。",
          "score": 0.5242164134979248
        },
        {
          "code": "IF-GU-540a.2",
          "text": "天然氣輸送基礎設施完整性。配送管線中：鑄鐵或鍛鐵、未受保護之鋼管的百分比。",
          "score": 0.4152783155441284
        }
      ]
    },
    {
      "id": 7,
      "text": "◎ 2022年董事會成員性別及年齡分布 (共11人)\n<table><tr><th>年齡</th><th>男性</th><th>女性</th></tr><tr><td>49歲以下</td><td>2</td><td>0</td></tr><tr><td>50-59歲</td><td>0</td><td>0</td></tr><tr><td>60-69歲</td><td>3</td><td>0</td></tr><tr><td>70歲以上</td><td>5</td><td>1</td></tr></table>",
      "bbox": [
        2063,
        1591,
        3464,
        1754
      ],
      "type": "table",
      "bbox_pdf": [
        989.9656391505126,
        763.6528012004926,
        1190.550048828125,
        841.8900146484375
      ],
      "retrieval": [
        {
          "code": "IF-GU-000.A",
          "text": "一般資訊。住宅、商業、工業客戶數。",
          "score": 0.5446737408638
        },
        {
          "code": "IF-GU-000.C",
          "text": "一般資訊。天然氣輸氣管線、配氣管線之長度。",
          "score": 0.478014200925827
        },
        {
          "code": "IF-GU-420a.2",
          "text": "終端使用效率。依市場別呈現因效率措施所節省之天然氣量。",
          "score": 0.46374422311782837
        },
        {
          "code": "IF-GU-000.B",
          "text": "一般資訊。向住宅、商業、工業客戶供應之天然氣量，以及轉供第三方之天然氣量。",
          "score": 0.4400651454925537
        },
        {
          "code": "IF-GU-540a.2",
          "text": "天然氣輸送基礎設施完整性。配送管線中：鑄鐵或鍛鐵、未受保護之鋼管的百分比。",
          "score": 0.3670540452003479
        }
      ]
    }
  ]
}