[
  {
    "bbox": [
      77.66,
      292.51,
      490.34,
      358.02
    ],
    "label": "Section-Header",
    "content": "<h2>人才吸引與留任</h2>",
    "bbox_pdf": [
      27.9576,
      105.3036,
      176.5224,
      128.8872
    ]
  },
  {
    "bbox": [
      374.61,
      440.29,
      703.53,
      478.38
    ],
    "label": "Section-Header",
    "content": "<h3>重大議題策略與目標</h3>",
    "bbox_pdf": [
      134.8596,
      158.5044,
      253.2708,
      172.2168
    ]
  },
  {
    "bbox": [
      77.66,
      551.51,
      228.42,
      620.07
    ],
    "label": "Section-Header",
    "content": "<h4>人才留任與員工關懷</h4>",
    "bbox_pdf": [
      27.9576,
      198.5436,
      82.2312,
      223.2252
    ]
  },
  {
    "bbox": [
      261.92,
      548.46,
      995.9,
      626.16
    ],
    "label": "Text",
    "content": "<p>傾聽並包容多元聲音，瞭解員工需求與想法，推動多元化留才措施及薪資福利活動，朝向幸福企業之路</p>",
    "bbox_pdf": [
      94.2912,
      197.4456,
      358.524,
      225.4176
    ]
  },
  {
    "bbox": [
      237.55,
      681.01,
      394.4,
      713.0
    ],
    "label": "Section-Header",
    "content": "<h4>2023年目標</h4>",
    "bbox_pdf": [
      85.518,
      245.1636,
      141.984,
      256.68
    ]
  },
  {
    "bbox": [
      77.66,
      751.09,
      548.2,
      993.32
    ],
    "label": "List-Group",
    "content": "<ul><li>離職率&lt;3%</li><li>關鍵績優員工留任率≥90%</li><li>員工滿意度分數達4.54</li><li>員工敬業度分數達4.70</li><li>暢通的勞資交流每年至少4次會議</li><li>開辦員工座談會2次</li></ul>",
    "bbox_pdf": [
      27.9576,
      270.3924,
      197.352,
      357.5952
    ]
  },
  {
    "bbox": [
      717.23,
      681.01,
      874.08,
      713.0
    ],
    "label": "Section-Header",
    "content": "<h4>2022年績效</h4>",
    "bbox_pdf": [
      258.2028,
      245.1636,
      314.6688,
      256.68
    ]
  },
  {
    "bbox": [
      599.98,
      798.32,
      988.29,
      956.76
    ],
    "label": "List-Group",
    "content": "<ul><li>離職率&lt;3%</li><li>關鍵績優員工留任率≥88%</li><li>暢通的勞資交流每年4次會議</li></ul>",
    "bbox_pdf": [
      215.9928,
      287.3952,
      355.7844,
      344.4336
    ]
  },
  {
    "bbox": [
      1142.09,
      336.69,
      1262.39,
      368.69
    ],
    "label": "Section-Header",
    "content": "<h4>人力結構</h4>",
    "bbox_pdf": [
      411.1524,
      121.2084,
      454.4604,
      132.7284
    ]
  },
  {
    "bbox": [
      1306.55,
      330.6,
      1349.19,
      354.98
    ],
    "label": "Text",
    "content": "2-7",
    "bbox_pdf": [
      470.358,
      119.016,
      485.7084,
      127.7928
    ]
  },
  {
    "bbox": [
      1404.01,
      330.6,
      1448.17,
      354.98
    ],
    "label": "Text",
    "content": "2-8",
    "bbox_pdf": [
      505.4436,
      119.016,
      521.3412,
      127.7928
    ]
  },
  {
    "bbox": [
      1486.24,
      330.6,
      1548.67,
      354.98
    ],
    "label": "Text",
    "content": "401-1",
    "bbox_pdf": [
      535.0464,
      119.016,
      557.5212,
      127.7928
    ]
  },
  {
    "bbox": [
      1586.74,
      330.6,
      1650.7,
      354.98
    ],
    "label": "Text",
    "content": "405-1",
    "bbox_pdf": [
      571.2264,
      119.016,
      594.252,
      127.7928
    ]
  },
  {
    "bbox": [
      1142.09,
      394.59,
      2203.47,
      470.76
    ],
    "label": "Text",
    "content": "<p>昇陽半導體秉持多元性與共容性，並制訂完善制度、遵循法規保障員工權益，以達到吸引與留任，力求公司與員工雙贏以及共同成長。</p>",
    "bbox_pdf": [
      411.1524,
      142.0524,
      793.2492,
      169.4736
    ]
  },
  {
    "bbox": [
      1142.09,
      495.14,
      2029.87,
      525.61
    ],
    "label": "Text",
    "content": "<p>截至2022年底，員工總數1,019人，其中男性員工比率佔72%、女性員工佔28%。</p>",
    "bbox_pdf": [
      411.1524,
      178.2504,
      730.7532,
      189.2196
    ]
  },
  {
    "bbox": [
      1230.41,
      598.74,
      1445.12,
      629.21
    ],
    "label": "Caption",
    "content": "<p>在職員工性別比例</p>",
    "bbox_pdf": [
      442.9476,
      215.5464,
      520.2432,
      226.5156
    ]
  },
  {
    "bbox": [
      1210.62,
      641.39,
      1495.38,
      958.28
    ],
    "label": "Figure",
    "content": "<p>Pie chart showing gender distribution: 72% Male, 28% Female.</p>",
    "bbox_pdf": [
      435.8232,
      230.9004,
      538.3368,
      344.9808
    ]
  },
  {
    "bbox": [
      1751.2,
      597.21,
      1964.39,
      626.16
    ],
    "label": "Caption",
    "content": "<p>在職員工年齡分布</p>",
    "bbox_pdf": [
      630.432,
      214.9956,
      707.1804,
      225.4176
    ]
  },
  {
    "bbox": [
      1726.84,
      641.39,
      2084.69,
      979.61
    ],
    "label": "Figure",
    "content": "<p>Pie chart showing age distribution: 71% 30-50 years, 23% 50+ years, 6% Under 30 years.</p>",
    "bbox_pdf": [
      621.6624,
      230.9004,
      750.4884,
      352.6596
    ]
  },
  {
    "bbox": [
      1114.68,
      1057.31,
      2179.11,
      1357.44
    ],
    "label": "Table",
    "content": "<table><thead><tr><th>分類</th><th></th><th>員工總人數</th><th>本國人數</th><th>外國人人數</th></tr></thead><tbody><tr><td rowspan=\"2\">性別</td><td>男性</td><td>730</td><td>581</td><td>149</td></tr><tr><td>女性</td><td>289</td><td>247</td><td>42</td></tr><tr><td>總計</td><td></td><td>1,019</td><td>828</td><td>191</td></tr><tr><td rowspan=\"3\">年齡</td><td>30歲以下</td><td>238</td><td>177</td><td>61</td></tr><tr><td>30-50歲</td><td>718</td><td>588</td><td>130</td></tr><tr><td>50歲以上</td><td>63</td><td>63</td><td>0</td></tr><tr><td>總計</td><td></td><td>1,019</td><td>828</td><td>191</td></tr></tbody></table>",
    "bbox_pdf": [
      401.2848,
      380.6316,
      784.4796,
      488.6784
    ]
  },
  {
    "bbox": [
      1116.2,
      1369.63,
      1381.17,
      1398.58
    ],
    "label": "Text",
    "content": "<p>註：本公司無非正式員工。</p>",
    "bbox_pdf": [
      401.832,
      493.0668,
      497.2212,
      503.4888
    ]
  },
  {
    "bbox": [
      2284.18,
      1410.76,
      2322.25,
      1436.66
    ],
    "label": "Page-Footer",
    "content": "59",
    "bbox_pdf": [
      822.3048,
      507.8736,
      836.01,
      517.1976
    ]
  }
]